<?xml version="1.0" encoding="UTF-8"?><root><Th><AFK and exercise therapy (Practice)><Starts>"08:20"</Starts><Ends>"09:50"</Ends><Teacher>"Platonova Valentina Aleksandrovna"</Teacher><Place>"room Борцовский зал (4506/1) ul. Lomonosova, d.9, lit. B"</Place></AFK and exercise therapy (Practice)><History of Russian science and technology (Lecture)><Starts>"11:40"</Starts><Ends>"13:10"</Ends><Teacher>"Vasilyev Andrey Vladimirovich"</Teacher><Place>"room 1404 Kronverksky pr., d.49, lit.A"</Place></History of Russian science and technology (Lecture)><History of Russian science and technology (Practice)><Starts>"15:20"</Starts><Ends>"16:50"</Ends><Teacher>"Vasilyev Andrey Vladimirovich"</Teacher><Place>"room 2430 Kronverksky pr., d.49, lit.A"</Place></History of Russian science and technology (Practice)></Th></root>